.gitignore
.travis.yml
CHANGES.rst
MANIFEST.in
README.rst
README.txt
bootstrap-buildout.py
bootstrap.py
bootstrap4.py
bootstrap5.py
buildout.cfg
setup.py
test-4.0.x.cfg
test-4.1.x.cfg
test-4.2.x.cfg
test-4.3.x.cfg
test-5.0.x.cfg
collective/__init__.py
collective.contentrules.mail.egg-info/PKG-INFO
collective.contentrules.mail.egg-info/SOURCES.txt
collective.contentrules.mail.egg-info/dependency_links.txt
collective.contentrules.mail.egg-info/entry_points.txt
collective.contentrules.mail.egg-info/namespace_packages.txt
collective.contentrules.mail.egg-info/not-zip-safe
collective.contentrules.mail.egg-info/requires.txt
collective.contentrules.mail.egg-info/top_level.txt
collective/contentrules/__init__.py
collective/contentrules/mail/__init__.py
collective/contentrules/mail/adapter.py
collective/contentrules/mail/configure.zcml
collective/contentrules/mail/interfaces.py
collective/contentrules/mail/model.py
collective/contentrules/mail/version.txt
collective/contentrules/mail/vocabulary.py
collective/contentrules/mail/actions/__init__.py
collective/contentrules/mail/actions/configure.zcml
collective/contentrules/mail/actions/mail.py
collective/contentrules/mail/browser/__init__.py
collective/contentrules/mail/browser/configure.zcml
collective/contentrules/mail/browser/widget.py
collective/contentrules/mail/browser/stylesheets/model.kss
collective/contentrules/mail/browser/templates/model.pt
collective/contentrules/mail/docs/README.txt
collective/contentrules/mail/doctests/README.txt
collective/contentrules/mail/profiles/default/kssregistry.xml
collective/contentrules/mail/profiles/default/metadata.xml
collective/contentrules/mail/profiles/testing/contentrules.xml
collective/contentrules/mail/profiles/testing/export_steps.xml
collective/contentrules/mail/profiles/testing/import_steps.xml
collective/contentrules/mail/tests/__init__.py
collective/contentrules/mail/tests/base.py
collective/contentrules/mail/tests/test_configuration.py
collective/contentrules/mail/tests/test_maildocs.py
collective/contentrules/mail/tests/test_maildocstrings.py
collective/contentrules/mail/tests/utils.py