Metadata-Version: 1.1
Name: collective.contentrules.mail
Version: 0.7
Summary: Flexible mail content rule
Home-page: https://github.com/collective/collective.contentrules.mail
Author: Ingeniweb
Author-email: support@ingeniweb.com
License: GPL
Platform: UNKNOWN
Classifier: Framework :: Plone
Classifier: Framework :: Plone :: 4.0
Classifier: Framework :: Plone :: 4.1
Classifier: Framework :: Plone :: 4.2
Classifier: Framework :: Plone :: 4.3
Classifier: Framework :: Plone :: 5.0
Classifier: Programming Language :: Python
Classifier: Programming Language :: Python :: 2.6
Classifier: Programming Language :: Python :: 2.7
Classifier: Topic :: Software Development :: Libraries :: Python Modules
